tests/__init__.py
tests/context.py
tests/test_bitwise_operators.py
tests/test_eval.py
tests/test_eval_array.py
tests/test_eval_list.py
tests/test_parser.py
tests/test_stdlib.py
tests/test_trace_eq.py
tests/test_trace_reader.py
tests/test_types.py
tests/test_varresolve.py
wal/__init__.py
wal/__main__.py
wal/ast_defs.py
wal/core.py
wal/eval.py
wal/passes.py
wal/reader.py
wal/repl.py
wal/spade.py
wal/util.py
wal/version.py
wal/wal.py
wal/walc.py
wal/implementation/__init__.py
wal/implementation/array.py
wal/implementation/bitwise.py
wal/implementation/core.py
wal/implementation/list.py
wal/implementation/math.py
wal/implementation/special.py
wal/implementation/types.py
wal/implementation/virtual.py
wal/implementation/wal.py
wal/libs/std/module.wal
wal/libs/std/module.wo
wal/libs/std/std.wal
wal/libs/std/std.wo
wal/trace/__init__.py
wal/trace/container.py
wal/trace/csvtrace.py
wal/trace/fst.py
wal/trace/trace.py
wal/trace/vcd.py
wal/trace/virtual.py
wal_lang-0.8.7.dist-info/licenses/LICENSE
walc/__init__.py
walc/__main__.py
wawk/__init__.py
wawk/ast_defs.py
wawk/parser.py
wawk/version.py
wawk/wawk.py
wal_lang-0.8.7.dist-info/METADATA
wal_lang-0.8.7.dist-info/WHEEL
wal_lang-0.8.7.dist-info/entry_points.txt
wal_lang-0.8.7.dist-info/top_level.txt
wal_lang-0.8.7.dist-info/RECORD
