Metadata-Version: 2.4
Name: wal-lang
Version: 0.8.7
Summary: Wal - Wavefile Analysis Language
Home-page: https://wal-lang.org
Author: Lucas Klemmer
Author-email: support@wal-lang.org
Keywords: verilog,VHDL,vcd,fst,development,hardware,rtl,simulation,verification,FPGA
Classifier: Topic :: Scientific/Engineering :: Electronic Design Automation (EDA)
Classifier: Development Status :: 4 - Beta
Classifier: Intended Audience :: Science/Research
Classifier: Intended Audience :: Developers
Classifier: License :: OSI Approved :: BSD License
Classifier: Programming Language :: Python :: 3
Classifier: Programming Language :: Python :: 3 :: Only
Classifier: Operating System :: OS Independent
Requires-Python: >=3.9, <4
License-File: LICENSE
Requires-Dist: lark
Provides-Extra: dev
Requires-Dist: ruff; extra == "dev"
Provides-Extra: test
Requires-Dist: coverage; extra == "test"
Dynamic: author
Dynamic: author-email
Dynamic: classifier
Dynamic: description
Dynamic: description-content-type
Dynamic: home-page
Dynamic: keywords
Dynamic: license-file
Dynamic: provides-extra
Dynamic: requires-dist
Dynamic: requires-python
Dynamic: summary
